[{"line":1,"elements":[{"line":3,"name":"","description":"","type":"background","keyword":"Background","steps":[{"result":{"status":"passed"},"line":4,"name":"The user is on flipKart home page","match":{"location":"stepdefinations.flipkart.NavigateToLOginPage.the_user_is_on_flip_kart_home_page()"},"keyword":"Given "}]},{"start_timestamp":"2024-12-28T18:10:48.876Z","before":[{"result":{"duration":14477555800,"status":"passed"},"match":{"location":"stepdefinations.flipkart.Add_to_Cart_Functionality.prepareed()"}},{"result":{"duration":2197611600,"status":"passed"},"match":{"location":"stepdefinations.flipkart.Enter_valid_email_and_navigate_to_opt_page.prepareed()"}},{"result":{"duration":6094353300,"status":"passed"},"match":{"location":"stepdefinations.flipkart.Max_Min_Price_Range_Filter.prepareed()"}},{"result":{"duration":2036758000,"status":"passed"},"match":{"location":"stepdefinations.flipkart.NavigateToLOginPage.prepareed()"}},{"result":{"duration":6052657100,"status":"passed"},"match":{"location":"stepdefinations.flipkart.Product_Search_Functionality.prepareed()"}},{"result":{"duration":1907079900,"status":"passed"},"match":{"location":"stepdefinations.flipkart.Verify_Flight_Search_Functionality.prepareed()"}}],"line":21,"name":"Search results are displayed for a valid product search","description":"","id":"verify-flight-search-functionality;search-results-are-displayed-for-a-valid-product-search;;2","after":[{"result":{"status":"passed"},"match":{"location":"stepdefinations.flipkart.Verify_Flight_Search_Functionality.tear()"}},{"result":{"duration":1000700,"status":"passed"},"match":{"location":"stepdefinations.flipkart.Product_Search_Functionality.tear()"}},{"result":{"duration":1000600,"status":"passed"},"match":{"location":"stepdefinations.flipkart.NavigateToLOginPage.tear()"}},{"result":{"status":"passed"},"match":{"location":"stepdefinations.flipkart.Max_Min_Price_Range_Filter.tear()"}},{"result":{"duration":999300,"status":"passed"},"match":{"location":"stepdefinations.flipkart.Enter_valid_email_and_navigate_to_opt_page.tear()"}},{"result":{"status":"passed"},"match":{"location":"stepdefinations.flipkart.Add_to_Cart_Functionality.tear()"}}],"type":"scenario","keyword":"Scenario Outline","steps":[{"result":{"duration":5814308400,"status":"passed"},"line":8,"name":"I click on Flights bookings","match":{"location":"stepdefinations.flipkart.Verify_Flight_Search_Functionality.i_click_on_flights_bookings()"},"keyword":"When "},{"result":{"duration":4015351300,"status":"passed"},"line":9,"name":"I should be navigated to flight search page","match":{"location":"stepdefinations.flipkart.Verify_Flight_Search_Functionality.i_should_be_navigated_to_flight_search_page()"},"keyword":"Then "},{"result":{"duration":797546400,"status":"passed"},"line":10,"name":"I select departure date \"February 2025,10\"","match":{"arguments":[{"val":"\"February 2025,10\"","offset":24}],"location":"stepdefinations.flipkart.Verify_Flight_Search_Functionality.i_select_departure_date(java.lang.String)"},"keyword":"And "},{"result":{"duration":5059646900,"status":"passed"},"line":11,"name":"I select return date \"April 2025,20\"","match":{"arguments":[{"val":"\"April 2025,20\"","offset":21}],"location":"stepdefinations.flipkart.Verify_Flight_Search_Functionality.i_select_return_date(java.lang.String)"},"keyword":"And "},{"result":{"duration":12475090200,"status":"passed"},"line":12,"name":"I select the departure city \"BOM\"","match":{"arguments":[{"val":"\"BOM\"","offset":28}],"location":"stepdefinations.flipkart.Verify_Flight_Search_Functionality.i_select_the_departure_city(java.lang.String)"},"keyword":"And "},{"result":{"duration":12567670100,"status":"passed"},"line":13,"name":"I select the destination city \"BKK\"","match":{"arguments":[{"val":"\"BKK\"","offset":30}],"location":"stepdefinations.flipkart.Verify_Flight_Search_Functionality.i_select_the_destination_city(java.lang.String)"},"keyword":"And "}],"tags":[{"name":"@Flight_Search"}]}],"name":"Verify Flight Search Functionality","description":"","id":"verify-flight-search-functionality","keyword":"Feature","uri":"file:src/test/resources/feature/flipKart/Verify_Flight_Search_Functionality.feature","tags":[]}]